{
    "id": 2264308434,
    "id_str": "2264308434",
    "name": "\u30af\u30ed\u30cf\u30ab\u30bb",
    "screen_name": "kurohakase8012",
    "location": "\u5c71\u53e3\u770c\u4e0b\u95a2\u5e02",
    "description": "\u3010#\u661f\u91ce\u6e90ANN\u3011 \u3010#\u4e43\u6728\u5742\u65b0\u5185ANN0\u3011 \u3010#bananamoon\u3011 \u3010#\u5927\u5009\u304f\u3093\u3068\u9ad8\u6a4b\u304f\u3093\u3011 \u3010#nhk\u3089\u3058\u3089\u30fc\uff08\u30b5\u30f3\u30c7\u30fc\u30fb\u4e43\u6728\u5742\u56de\uff09\u3011 \u3010#reco1134\uff08\u6c34\u66dc0\u6642\u53f0\u306e\u307f\uff09\u3011  \uff0f\u7af6\u99ac\uff0f\u30d7\u30ed\u91ce\u7403\uff08\u9df9\u5bc4\u308a\u306eDD\uff09\uff0f\u30a2\u30f3\u30c1LDH\uff06\u30b9\u30bf\u30c0\uff0f\u4e43\u6728\u5742ANN\u306e\u65e9\u671f\u5b9f\u73fe\u3092\uff01",
    "url": "https://t.co/K9JAd1gV29",
    "entities": {
        "url": {
            "urls": [
                {
                    "url": "https://t.co/K9JAd1gV29",
                    "expanded_url": "http://ameblo.jp/kurohakase8012-blog/",
                    "display_url": "ameblo.jp/kurohakase8012\u2026",
                    "indices": [
                        0,
                        23
                    ]
                }
            ]
        },
        "description": {
            "urls": []
        }
    },
    "protected": false,
    "followers_count": 397,
    "fast_followers_count": 0,
    "normal_followers_count": 397,
    "friends_count": 478,
    "listed_count": 12,
    "created_at": "Fri Dec 27 12:55:34 +0000 2013",
    "favourites_count": 7551,
    "utc_offset": 32400,
    "time_zone": "Osaka",
    "geo_enabled": false,
    "verified": false,
    "statuses_count": 128290,
    "media_count": 691,
    "lang": "ja",
    "status": {
        "created_at": "Wed Jul 19 19:51:07 +0000 2017",
        "id": 887761739911012352,
        "id_str": "887761739911012352",
        "text": "\ud83d\ude34\ud83d\udca4",
        "truncated": false,
        "entities": {
            "hashtags": [],
            "symbols": [],
            "user_mentions": [],
            "urls": []
        },
        "source": "<a href=\"http://twitter.com\" rel=\"nofollow\">Twitter Web Client</a>",
        "in_reply_to_status_id": null,
        "in_reply_to_status_id_str": null,
        "in_reply_to_user_id": null,
        "in_reply_to_user_id_str": null,
        "in_reply_to_screen_name": null,
        "geo": null,
        "coordinates": null,
        "place": null,
        "contributors": null,
        "is_quote_status": false,
        "retweet_count": 0,
        "favorite_count": 0,
        "favorited": false,
        "retweeted": false,
        "lang": "und",
        "supplemental_language": null
    },
    "contributors_enabled": false,
    "is_translator": false,
    "is_translation_enabled": false,
    "profile_background_color": "000000",
    "profile_background_image_url": "http://abs.twimg.com/images/themes/theme1/bg.png",
    "profile_background_image_url_https": "https://abs.twimg.com/images/themes/theme1/bg.png",
    "profile_background_tile": false,
    "profile_image_url": "http://pbs.twimg.com/profile_images/763629656192843781/RKNqF2XR_normal.jpg",
    "profile_image_url_https": "https://pbs.twimg.com/profile_images/763629656192843781/RKNqF2XR_normal.jpg",
    "profile_link_color": "1B95E0",
    "profile_sidebar_border_color": "000000",
    "profile_sidebar_fill_color": "000000",
    "profile_text_color": "000000",
    "profile_use_background_image": false,
    "has_extended_profile": true,
    "default_profile": false,
    "default_profile_image": false,
    "has_custom_timelines": false,
    "can_media_tag": true,
    "followed_by": false,
    "following": false,
    "follow_request_sent": false,
    "notifications": false,
    "business_profile_state": "none",
    "translator_type": "none"
}