{
    "id": 264189578,
    "id_str": "264189578",
    "name": "\u3051\u3093\u3077\u3075\u3041\u30fc",
    "screen_name": "ms18ekenpu",
    "location": "\u304b\u304c\u308f\u3061\u307b\u30fc",
    "description": "\u30ac\u30f3\u30c0\u30e0/\u30ac\u30eb\u30d1\u30f3/\u30c1\u30e3\u30fc\u7814/\u30dd\u30ed\u30f3/\u30d1\u30c8\u30ec\u30a4\u30d0\u30fc/\u8266\u3053\u308c/\u30c7\u30ec\u30b9\u30c6/FA\u30ac\u30fc\u30eb/\u81ea\u885b\u968a\uff65\u8ecd\u4e8b/\u30d7\u30e9\u30e2\u30c7\u30eb\u30fb\u30d5\u30a3\u30ae\u30e5\u30a2/\u30a4\u30e9\u30b9\u30c8\u63cf\u304d\u307e\u3059/\u7965\u9cf3\u30fb\u897f\u4f4f\u307f\u307b\u30fb\u6cc9\u7814\u30fb\u6afb\u4e95\u6843\u83ef\u30fb\u30ac\u30f3\u30bf\u30f3\u30af\u597d\u304d\u3067\u3059/\u300c\u661f\u306e\u5b50\u30dd\u30ed\u30f3\u300d\u300c\u30ac\u30f3\u3068\u30b4\u30f3\u300d\u63a2\u3057\u3066\u307e\u3059/\u8a73\u3057\u304f\u306f\u4e0b\u8a18URL\u306b\u3066",
    "url": "https://t.co/lH8GSwXSXk",
    "entities": {
        "url": {
            "urls": [
                {
                    "url": "https://t.co/lH8GSwXSXk",
                    "expanded_url": "http://twpf.jp/ms18ekenpu",
                    "display_url": "twpf.jp/ms18ekenpu",
                    "indices": [
                        0,
                        23
                    ]
                }
            ]
        },
        "description": {
            "urls": []
        }
    },
    "protected": false,
    "followers_count": 733,
    "fast_followers_count": 0,
    "normal_followers_count": 733,
    "friends_count": 1450,
    "listed_count": 21,
    "created_at": "Fri Mar 11 13:57:28 +0000 2011",
    "favourites_count": 75489,
    "utc_offset": 32400,
    "time_zone": "Tokyo",
    "geo_enabled": true,
    "verified": false,
    "statuses_count": 56180,
    "media_count": 3190,
    "lang": "ja",
    "status": {
        "created_at": "Thu Jul 20 00:26:58 +0000 2017",
        "id": 887831160658604032,
        "id_str": "887831160658604032",
        "text": "RT @ms18ekenpu: \u30b9\u30b4\u30b9\u30b4\u30a4\u30a4\u30f3\u30c7\u30b9\u30e8\u30cd\u30b8\u300c\u30a4\u30a4\u30f3\u30c7\u30b9\u30e8\u30a9\uff5e\u3001\u3053\u3093\u306a\u306b\u304a\u5ba2\u3092\u96c6\u3081\u3066\u3082\u3089\u3063\u3066\u30a4\u30a4\u30f3\u30c7\u30b9\u30e8\u30a9\uff5e\u300d https://t.co/Ijn1qzurex",
        "truncated": false,
        "entities": {
            "hashtags": [],
            "symbols": [],
            "user_mentions": [
                {
                    "screen_name": "ms18ekenpu",
                    "name": "\u3051\u3093\u3077\u3075\u3041\u30fc",
                    "id": 264189578,
                    "id_str": "264189578",
                    "indices": [
                        3,
                        14
                    ]
                }
            ],
            "urls": [],
            "media": [
                {
                    "id": 885892777287983104,
                    "id_str": "885892777287983104",
                    "indices": [
                        62,
                        85
                    ],
                    "media_url": "http://pbs.twimg.com/media/DEtSyYtVoAAb3wI.jpg",
                    "media_url_https": "https://pbs.twimg.com/media/DEtSyYtVoAAb3wI.jpg",
                    "url": "https://t.co/Ijn1qzurex",
                    "display_url": "pic.twitter.com/Ijn1qzurex",
                    "expanded_url": "https://twitter.com/ms18ekenpu/status/885892798519562241/photo/1",
                    "type": "photo",
                    "sizes": {
                        "medium": {
                            "w": 1200,
                            "h": 675,
                            "resize": "fit"
                        },
                        "thumb": {
                            "w": 150,
                            "h": 150,
                            "resize": "crop"
                        },
                        "small": {
                            "w": 680,
                            "h": 382,
                            "resize": "fit"
                        },
                        "large": {
                            "w": 1311,
                            "h": 737,
                            "resize": "fit"
                        }
                    },
                    "source_status_id": 885892798519562241,
                    "source_status_id_str": "885892798519562241",
                    "source_user_id": 264189578,
                    "source_user_id_str": "264189578",
                    "features": {
                        "medium": {
                            "faces": [
                                {
                                    "x": 543,
                                    "y": 140,
                                    "h": 97,
                                    "w": 97
                                },
                                {
                                    "x": 257,
                                    "y": 318,
                                    "h": 199,
                                    "w": 199
                                }
                            ]
                        },
                        "orig": {
                            "faces": [
                                {
                                    "x": 594,
                                    "y": 153,
                                    "h": 107,
                                    "w": 107
                                },
                                {
                                    "x": 281,
                                    "y": 348,
                                    "h": 218,
                                    "w": 218
                                }
                            ]
                        },
                        "small": {
                            "faces": [
                                {
                                    "x": 308,
                                    "y": 79,
                                    "h": 55,
                                    "w": 55
                                },
                                {
                                    "x": 145,
                                    "y": 180,
                                    "h": 113,
                                    "w": 113
                                }
                            ]
                        },
                        "large": {
                            "faces": [
                                {
                                    "x": 594,
                                    "y": 153,
                                    "h": 107,
                                    "w": 107
                                },
                                {
                                    "x": 281,
                                    "y": 348,
                                    "h": 218,
                                    "w": 218
                                }
                            ]
                        }
                    }
                }
            ]
        },
        "extended_entities": {
            "media": [
                {
                    "id": 885892777287983104,
                    "id_str": "885892777287983104",
                    "indices": [
                        62,
                        85
                    ],
                    "media_url": "http://pbs.twimg.com/media/DEtSyYtVoAAb3wI.jpg",
                    "media_url_https": "https://pbs.twimg.com/media/DEtSyYtVoAAb3wI.jpg",
                    "url": "https://t.co/Ijn1qzurex",
                    "display_url": "pic.twitter.com/Ijn1qzurex",
                    "expanded_url": "https://twitter.com/ms18ekenpu/status/885892798519562241/photo/1",
                    "type": "photo",
                    "sizes": {
                        "medium": {
                            "w": 1200,
                            "h": 675,
                            "resize": "fit"
                        },
                        "thumb": {
                            "w": 150,
                            "h": 150,
                            "resize": "crop"
                        },
                        "small": {
                            "w": 680,
                            "h": 382,
                            "resize": "fit"
                        },
                        "large": {
                            "w": 1311,
                            "h": 737,
                            "resize": "fit"
                        }
                    },
                    "source_status_id": 885892798519562241,
                    "source_status_id_str": "885892798519562241",
                    "source_user_id": 264189578,
                    "source_user_id_str": "264189578",
                    "features": {
                        "medium": {
                            "faces": [
                                {
                                    "x": 543,
                                    "y": 140,
                                    "h": 97,
                                    "w": 97
                                },
                                {
                                    "x": 257,
                                    "y": 318,
                                    "h": 199,
                                    "w": 199
                                }
                            ]
                        },
                        "orig": {
                            "faces": [
                                {
                                    "x": 594,
                                    "y": 153,
                                    "h": 107,
                                    "w": 107
                                },
                                {
                                    "x": 281,
                                    "y": 348,
                                    "h": 218,
                                    "w": 218
                                }
                            ]
                        },
                        "small": {
                            "faces": [
                                {
                                    "x": 308,
                                    "y": 79,
                                    "h": 55,
                                    "w": 55
                                },
                                {
                                    "x": 145,
                                    "y": 180,
                                    "h": 113,
                                    "w": 113
                                }
                            ]
                        },
                        "large": {
                            "faces": [
                                {
                                    "x": 594,
                                    "y": 153,
                                    "h": 107,
                                    "w": 107
                                },
                                {
                                    "x": 281,
                                    "y": 348,
                                    "h": 218,
                                    "w": 218
                                }
                            ]
                        }
                    }
                }
            ]
        },
        "source": "<a href=\"http://twitter.com/download/android\" rel=\"nofollow\">Twitter for Android</a>",
        "in_reply_to_status_id": null,
        "in_reply_to_status_id_str": null,
        "in_reply_to_user_id": null,
        "in_reply_to_user_id_str": null,
        "in_reply_to_screen_name": null,
        "geo": null,
        "coordinates": null,
        "place": null,
        "contributors": null,
        "retweeted_status": {
            "created_at": "Fri Jul 14 16:04:36 +0000 2017",
            "id": 885892798519562241,
            "id_str": "885892798519562241",
            "text": "\u30b9\u30b4\u30b9\u30b4\u30a4\u30a4\u30f3\u30c7\u30b9\u30e8\u30cd\u30b8\u300c\u30a4\u30a4\u30f3\u30c7\u30b9\u30e8\u30a9\uff5e\u3001\u3053\u3093\u306a\u306b\u304a\u5ba2\u3092\u96c6\u3081\u3066\u3082\u3089\u3063\u3066\u30a4\u30a4\u30f3\u30c7\u30b9\u30e8\u30a9\uff5e\u300d https://t.co/Ijn1qzurex",
            "truncated": false,
            "entities": {
                "hashtags": [],
                "symbols": [],
                "user_mentions": [],
                "urls": [],
                "media": [
                    {
                        "id": 885892777287983104,
                        "id_str": "885892777287983104",
                        "indices": [
                            46,
                            69
                        ],
                        "media_url": "http://pbs.twimg.com/media/DEtSyYtVoAAb3wI.jpg",
                        "media_url_https": "https://pbs.twimg.com/media/DEtSyYtVoAAb3wI.jpg",
                        "url": "https://t.co/Ijn1qzurex",
                        "display_url": "pic.twitter.com/Ijn1qzurex",
                        "expanded_url": "https://twitter.com/ms18ekenpu/status/885892798519562241/photo/1",
                        "type": "photo",
                        "sizes": {
                            "medium": {
                                "w": 1200,
                                "h": 675,
                                "resize": "fit"
                            },
                            "thumb": {
                                "w": 150,
                                "h": 150,
                                "resize": "crop"
                            },
                            "small": {
                                "w": 680,
                                "h": 382,
                                "resize": "fit"
                            },
                            "large": {
                                "w": 1311,
                                "h": 737,
                                "resize": "fit"
                            }
                        },
                        "features": {
                            "medium": {
                                "faces": [
                                    {
                                        "x": 543,
                                        "y": 140,
                                        "h": 97,
                                        "w": 97
                                    },
                                    {
                                        "x": 257,
                                        "y": 318,
                                        "h": 199,
                                        "w": 199
                                    }
                                ]
                            },
                            "orig": {
                                "faces": [
                                    {
                                        "x": 594,
                                        "y": 153,
                                        "h": 107,
                                        "w": 107
                                    },
                                    {
                                        "x": 281,
                                        "y": 348,
                                        "h": 218,
                                        "w": 218
                                    }
                                ]
                            },
                            "small": {
                                "faces": [
                                    {
                                        "x": 308,
                                        "y": 79,
                                        "h": 55,
                                        "w": 55
                                    },
                                    {
                                        "x": 145,
                                        "y": 180,
                                        "h": 113,
                                        "w": 113
                                    }
                                ]
                            },
                            "large": {
                                "faces": [
                                    {
                                        "x": 594,
                                        "y": 153,
                                        "h": 107,
                                        "w": 107
                                    },
                                    {
                                        "x": 281,
                                        "y": 348,
                                        "h": 218,
                                        "w": 218
                                    }
                                ]
                            }
                        }
                    }
                ]
            },
            "extended_entities": {
                "media": [
                    {
                        "id": 885892777287983104,
                        "id_str": "885892777287983104",
                        "indices": [
                            46,
                            69
                        ],
                        "media_url": "http://pbs.twimg.com/media/DEtSyYtVoAAb3wI.jpg",
                        "media_url_https": "https://pbs.twimg.com/media/DEtSyYtVoAAb3wI.jpg",
                        "url": "https://t.co/Ijn1qzurex",
                        "display_url": "pic.twitter.com/Ijn1qzurex",
                        "expanded_url": "https://twitter.com/ms18ekenpu/status/885892798519562241/photo/1",
                        "type": "photo",
                        "sizes": {
                            "medium": {
                                "w": 1200,
                                "h": 675,
                                "resize": "fit"
                            },
                            "thumb": {
                                "w": 150,
                                "h": 150,
                                "resize": "crop"
                            },
                            "small": {
                                "w": 680,
                                "h": 382,
                                "resize": "fit"
                            },
                            "large": {
                                "w": 1311,
                                "h": 737,
                                "resize": "fit"
                            }
                        },
                        "features": {
                            "medium": {
                                "faces": [
                                    {
                                        "x": 543,
                                        "y": 140,
                                        "h": 97,
                                        "w": 97
                                    },
                                    {
                                        "x": 257,
                                        "y": 318,
                                        "h": 199,
                                        "w": 199
                                    }
                                ]
                            },
                            "orig": {
                                "faces": [
                                    {
                                        "x": 594,
                                        "y": 153,
                                        "h": 107,
                                        "w": 107
                                    },
                                    {
                                        "x": 281,
                                        "y": 348,
                                        "h": 218,
                                        "w": 218
                                    }
                                ]
                            },
                            "small": {
                                "faces": [
                                    {
                                        "x": 308,
                                        "y": 79,
                                        "h": 55,
                                        "w": 55
                                    },
                                    {
                                        "x": 145,
                                        "y": 180,
                                        "h": 113,
                                        "w": 113
                                    }
                                ]
                            },
                            "large": {
                                "faces": [
                                    {
                                        "x": 594,
                                        "y": 153,
                                        "h": 107,
                                        "w": 107
                                    },
                                    {
                                        "x": 281,
                                        "y": 348,
                                        "h": 218,
                                        "w": 218
                                    }
                                ]
                            }
                        }
                    }
                ]
            },
            "source": "<a href=\"http://twitter.com/download/android\" rel=\"nofollow\">Twitter for Android</a>",
            "in_reply_to_status_id": null,
            "in_reply_to_status_id_str": null,
            "in_reply_to_user_id": null,
            "in_reply_to_user_id_str": null,
            "in_reply_to_screen_name": null,
            "geo": null,
            "coordinates": null,
            "place": null,
            "contributors": null,
            "is_quote_status": false,
            "retweet_count": 1,
            "favorite_count": 10,
            "favorited": false,
            "retweeted": false,
            "possibly_sensitive": false,
            "lang": "ja",
            "supplemental_language": null
        },
        "is_quote_status": false,
        "retweet_count": 1,
        "favorite_count": 0,
        "favorited": false,
        "retweeted": false,
        "possibly_sensitive": false,
        "lang": "ja",
        "supplemental_language": null
    },
    "contributors_enabled": false,
    "is_translator": false,
    "is_translation_enabled": false,
    "profile_background_color": "C0DEED",
    "profile_background_image_url": "http://abs.twimg.com/images/themes/theme1/bg.png",
    "profile_background_image_url_https": "https://abs.twimg.com/images/themes/theme1/bg.png",
    "profile_background_tile": false,
    "profile_image_url": "http://pbs.twimg.com/profile_images/880806234873503744/3SloltL7_normal.jpg",
    "profile_image_url_https": "https://pbs.twimg.com/profile_images/880806234873503744/3SloltL7_normal.jpg",
    "profile_banner_url": "https://pbs.twimg.com/profile_banners/264189578/1492869190",
    "profile_link_color": "1DA1F2",
    "profile_sidebar_border_color": "C0DEED",
    "profile_sidebar_fill_color": "DDEEF6",
    "profile_text_color": "333333",
    "profile_use_background_image": true,
    "has_extended_profile": true,
    "default_profile": true,
    "default_profile_image": false,
    "has_custom_timelines": false,
    "can_media_tag": true,
    "followed_by": false,
    "following": false,
    "follow_request_sent": false,
    "notifications": false,
    "business_profile_state": "none",
    "translator_type": "none"
}