{
    "id": 1501772856,
    "id_str": "1501772856",
    "name": "\u305d\u3089\u3061@\u7a7a/\u3074\u30fc\u305d\u2192\u4e03\u97f3\u6fc0\u63a8\u3057\u262a\ufe0e.\u00b0",
    "screen_name": "sora03196",
    "location": " \u6211\u3089\u5929\u4e0b\u7121\u6575\u306e\u3074\u3085\u3070\u3053\u3093\u3073  CHUNITHM NET",
    "description": "\u95a2\u897f\u5728\u4f4f\u3002\u30b2\u30fc\u30e0\u3068\u30a2\u30cb\u30e1\u597d\u304d\u306e\u7537\u3002\u5927\u5b66\u751f\u3002\u81ea\u5206\u306a\u308a\u306e\u52aa\u529b\u4e2d\u3002\u82b1\u5712\u5927\u5b66\u793e\u4f1a\u798f\u7949\u5b66\u79d11\u56de\u751f\u3002LINE\u4ea4\u63dbOK \u306e\u3093\u305f\u3093\u306e\u4eba\u3002\u30c1\u30e5\u30a6\u30cb\u30ba\u30de\u30fc\u306a\u30de\u30a4\u30de\u30a4\u30de\u30fc\u3002\u81ea\u79f0\u30e9\u30a4\u30d0\u30fc \u97f3\u30b2\u30fc\u30a8\u30f3\u30b8\u30e7\u30a4\u52e2\u3002\u30a2\u30a4\u30b3\u30f3\u2192\u5ac1 \u30d8\u30c3\u30c0\u30fc\u2192\u3089\u3063\u304f\u3093 \u63a8\u3057\u30e1\u30f3\u2192\u03bc's \u5e0c Aqorus \u304b\u306a\u307e\u308a\u3001\u82b1\u4e38 \u97f3\u30b2\u30fc\u2192CHUNITHM maimai \u30c0\u30f3\u30a8\u30dc",
    "url": "https://t.co/wFdX45Mx5h",
    "entities": {
        "url": {
            "urls": [
                {
                    "url": "https://t.co/wFdX45Mx5h",
                    "expanded_url": "http://twpf.jp/sora03196",
                    "display_url": "twpf.jp/sora03196",
                    "indices": [
                        0,
                        23
                    ]
                }
            ]
        },
        "description": {
            "urls": []
        }
    },
    "protected": false,
    "followers_count": 3746,
    "fast_followers_count": 0,
    "normal_followers_count": 3746,
    "friends_count": 4987,
    "listed_count": 46,
    "created_at": "Tue Jun 11 10:49:11 +0000 2013",
    "favourites_count": 20625,
    "utc_offset": null,
    "time_zone": null,
    "geo_enabled": false,
    "verified": false,
    "statuses_count": 30920,
    "media_count": 6305,
    "lang": "ja",
    "status": {
        "created_at": "Thu Jul 20 00:13:22 +0000 2017",
        "id": 887827738001678336,
        "id_str": "887827738001678336",
        "text": "RT @0pis0: \u516c\u5f0f\u306b\u3088\u308b\u8cb4\u91cd\u306a\uff62\u30a6\u30c7\u30de\u30a8\uff63\u306e\u5b9a\u7fa9\u3060\u3002\u3053\u308c\u672c\u8cea\u304b\u3082\u3057\u308c\u3093\u3051\u3069\u3001\u5b9f\u969b\u306b\u30ac\u30c1\u30de\u3084\u3063\u3066\u308b\u3046\u3061\u306b\u7d76\u5bfe\u5fd8\u308c\u305d\u3046\u3060\u304b\u3089\u5fc3\u306b\u7559\u3081\u3066\u304a\u3053\u3046\u2026\u3002 https://t.co/b3iLVi7X6c",
        "truncated": false,
        "entities": {
            "hashtags": [],
            "symbols": [],
            "user_mentions": [
                {
                    "screen_name": "0pis0",
                    "name": "\u30ec\u30a3\u30c3\u30d4\u30bd",
                    "id": 3017737492,
                    "id_str": "3017737492",
                    "indices": [
                        3,
                        9
                    ]
                }
            ],
            "urls": [],
            "media": [
                {
                    "id": 886875726170865664,
                    "id_str": "886875726170865664",
                    "indices": [
                        75,
                        98
                    ],
                    "media_url": "http://pbs.twimg.com/media/DE7QxipUwAAI_H8.jpg",
                    "media_url_https": "https://pbs.twimg.com/media/DE7QxipUwAAI_H8.jpg",
                    "url": "https://t.co/b3iLVi7X6c",
                    "display_url": "pic.twitter.com/b3iLVi7X6c",
                    "expanded_url": "https://twitter.com/0pis0/status/886875733359972354/photo/1",
                    "type": "photo",
                    "sizes": {
                        "small": {
                            "w": 508,
                            "h": 680,
                            "resize": "fit"
                        },
                        "thumb": {
                            "w": 150,
                            "h": 150,
                            "resize": "crop"
                        },
                        "medium": {
                            "w": 750,
                            "h": 1003,
                            "resize": "fit"
                        },
                        "large": {
                            "w": 750,
                            "h": 1003,
                            "resize": "fit"
                        }
                    },
                    "source_status_id": 886875733359972354,
                    "source_status_id_str": "886875733359972354",
                    "source_user_id": 3017737492,
                    "source_user_id_str": "3017737492",
                    "features": {
                        "orig": {
                            "faces": [
                                {
                                    "x": 44,
                                    "y": 63,
                                    "h": 64,
                                    "w": 64
                                }
                            ]
                        },
                        "small": {
                            "faces": [
                                {
                                    "x": 29,
                                    "y": 42,
                                    "h": 43,
                                    "w": 43
                                }
                            ]
                        },
                        "medium": {
                            "faces": [
                                {
                                    "x": 44,
                                    "y": 63,
                                    "h": 64,
                                    "w": 64
                                }
                            ]
                        },
                        "large": {
                            "faces": [
                                {
                                    "x": 44,
                                    "y": 63,
                                    "h": 64,
                                    "w": 64
                                }
                            ]
                        }
                    }
                }
            ]
        },
        "extended_entities": {
            "media": [
                {
                    "id": 886875726170865664,
                    "id_str": "886875726170865664",
                    "indices": [
                        75,
                        98
                    ],
                    "media_url": "http://pbs.twimg.com/media/DE7QxipUwAAI_H8.jpg",
                    "media_url_https": "https://pbs.twimg.com/media/DE7QxipUwAAI_H8.jpg",
                    "url": "https://t.co/b3iLVi7X6c",
                    "display_url": "pic.twitter.com/b3iLVi7X6c",
                    "expanded_url": "https://twitter.com/0pis0/status/886875733359972354/photo/1",
                    "type": "photo",
                    "sizes": {
                        "small": {
                            "w": 508,
                            "h": 680,
                            "resize": "fit"
                        },
                        "thumb": {
                            "w": 150,
                            "h": 150,
                            "resize": "crop"
                        },
                        "medium": {
                            "w": 750,
                            "h": 1003,
                            "resize": "fit"
                        },
                        "large": {
                            "w": 750,
                            "h": 1003,
                            "resize": "fit"
                        }
                    },
                    "source_status_id": 886875733359972354,
                    "source_status_id_str": "886875733359972354",
                    "source_user_id": 3017737492,
                    "source_user_id_str": "3017737492",
                    "features": {
                        "orig": {
                            "faces": [
                                {
                                    "x": 44,
                                    "y": 63,
                                    "h": 64,
                                    "w": 64
                                }
                            ]
                        },
                        "small": {
                            "faces": [
                                {
                                    "x": 29,
                                    "y": 42,
                                    "h": 43,
                                    "w": 43
                                }
                            ]
                        },
                        "medium": {
                            "faces": [
                                {
                                    "x": 44,
                                    "y": 63,
                                    "h": 64,
                                    "w": 64
                                }
                            ]
                        },
                        "large": {
                            "faces": [
                                {
                                    "x": 44,
                                    "y": 63,
                                    "h": 64,
                                    "w": 64
                                }
                            ]
                        }
                    }
                }
            ]
        },
        "source": "<a href=\"http://twitter.com/download/iphone\" rel=\"nofollow\">Twitter for iPhone</a>",
        "in_reply_to_status_id": null,
        "in_reply_to_status_id_str": null,
        "in_reply_to_user_id": null,
        "in_reply_to_user_id_str": null,
        "in_reply_to_screen_name": null,
        "geo": null,
        "coordinates": null,
        "place": null,
        "contributors": null,
        "retweeted_status": {
            "created_at": "Mon Jul 17 09:10:26 +0000 2017",
            "id": 886875733359972354,
            "id_str": "886875733359972354",
            "text": "\u516c\u5f0f\u306b\u3088\u308b\u8cb4\u91cd\u306a\uff62\u30a6\u30c7\u30de\u30a8\uff63\u306e\u5b9a\u7fa9\u3060\u3002\u3053\u308c\u672c\u8cea\u304b\u3082\u3057\u308c\u3093\u3051\u3069\u3001\u5b9f\u969b\u306b\u30ac\u30c1\u30de\u3084\u3063\u3066\u308b\u3046\u3061\u306b\u7d76\u5bfe\u5fd8\u308c\u305d\u3046\u3060\u304b\u3089\u5fc3\u306b\u7559\u3081\u3066\u304a\u3053\u3046\u2026\u3002 https://t.co/b3iLVi7X6c",
            "truncated": false,
            "entities": {
                "hashtags": [],
                "symbols": [],
                "user_mentions": [],
                "urls": [],
                "media": [
                    {
                        "id": 886875726170865664,
                        "id_str": "886875726170865664",
                        "indices": [
                            64,
                            87
                        ],
                        "media_url": "http://pbs.twimg.com/media/DE7QxipUwAAI_H8.jpg",
                        "media_url_https": "https://pbs.twimg.com/media/DE7QxipUwAAI_H8.jpg",
                        "url": "https://t.co/b3iLVi7X6c",
                        "display_url": "pic.twitter.com/b3iLVi7X6c",
                        "expanded_url": "https://twitter.com/0pis0/status/886875733359972354/photo/1",
                        "type": "photo",
                        "sizes": {
                            "small": {
                                "w": 508,
                                "h": 680,
                                "resize": "fit"
                            },
                            "thumb": {
                                "w": 150,
                                "h": 150,
                                "resize": "crop"
                            },
                            "medium": {
                                "w": 750,
                                "h": 1003,
                                "resize": "fit"
                            },
                            "large": {
                                "w": 750,
                                "h": 1003,
                                "resize": "fit"
                            }
                        },
                        "features": {
                            "orig": {
                                "faces": [
                                    {
                                        "x": 44,
                                        "y": 63,
                                        "h": 64,
                                        "w": 64
                                    }
                                ]
                            },
                            "small": {
                                "faces": [
                                    {
                                        "x": 29,
                                        "y": 42,
                                        "h": 43,
                                        "w": 43
                                    }
                                ]
                            },
                            "medium": {
                                "faces": [
                                    {
                                        "x": 44,
                                        "y": 63,
                                        "h": 64,
                                        "w": 64
                                    }
                                ]
                            },
                            "large": {
                                "faces": [
                                    {
                                        "x": 44,
                                        "y": 63,
                                        "h": 64,
                                        "w": 64
                                    }
                                ]
                            }
                        }
                    }
                ]
            },
            "extended_entities": {
                "media": [
                    {
                        "id": 886875726170865664,
                        "id_str": "886875726170865664",
                        "indices": [
                            64,
                            87
                        ],
                        "media_url": "http://pbs.twimg.com/media/DE7QxipUwAAI_H8.jpg",
                        "media_url_https": "https://pbs.twimg.com/media/DE7QxipUwAAI_H8.jpg",
                        "url": "https://t.co/b3iLVi7X6c",
                        "display_url": "pic.twitter.com/b3iLVi7X6c",
                        "expanded_url": "https://twitter.com/0pis0/status/886875733359972354/photo/1",
                        "type": "photo",
                        "sizes": {
                            "small": {
                                "w": 508,
                                "h": 680,
                                "resize": "fit"
                            },
                            "thumb": {
                                "w": 150,
                                "h": 150,
                                "resize": "crop"
                            },
                            "medium": {
                                "w": 750,
                                "h": 1003,
                                "resize": "fit"
                            },
                            "large": {
                                "w": 750,
                                "h": 1003,
                                "resize": "fit"
                            }
                        },
                        "features": {
                            "orig": {
                                "faces": [
                                    {
                                        "x": 44,
                                        "y": 63,
                                        "h": 64,
                                        "w": 64
                                    }
                                ]
                            },
                            "small": {
                                "faces": [
                                    {
                                        "x": 29,
                                        "y": 42,
                                        "h": 43,
                                        "w": 43
                                    }
                                ]
                            },
                            "medium": {
                                "faces": [
                                    {
                                        "x": 44,
                                        "y": 63,
                                        "h": 64,
                                        "w": 64
                                    }
                                ]
                            },
                            "large": {
                                "faces": [
                                    {
                                        "x": 44,
                                        "y": 63,
                                        "h": 64,
                                        "w": 64
                                    }
                                ]
                            }
                        }
                    }
                ]
            },
            "source": "<a href=\"http://twitter.com/download/iphone\" rel=\"nofollow\">Twitter for iPhone</a>",
            "in_reply_to_status_id": null,
            "in_reply_to_status_id_str": null,
            "in_reply_to_user_id": null,
            "in_reply_to_user_id_str": null,
            "in_reply_to_screen_name": null,
            "geo": null,
            "coordinates": null,
            "place": null,
            "contributors": null,
            "is_quote_status": false,
            "retweet_count": 5965,
            "favorite_count": 6238,
            "favorited": false,
            "retweeted": false,
            "possibly_sensitive": false,
            "lang": "ja",
            "supplemental_language": null
        },
        "is_quote_status": false,
        "retweet_count": 5965,
        "favorite_count": 0,
        "favorited": false,
        "retweeted": false,
        "possibly_sensitive": false,
        "lang": "ja",
        "supplemental_language": null
    },
    "contributors_enabled": false,
    "is_translator": false,
    "is_translation_enabled": false,
    "profile_background_color": "C0DEED",
    "profile_background_image_url": "http://abs.twimg.com/images/themes/theme1/bg.png",
    "profile_background_image_url_https": "https://abs.twimg.com/images/themes/theme1/bg.png",
    "profile_background_tile": false,
    "profile_image_url": "http://pbs.twimg.com/profile_images/871084233292267520/_esWF_cy_normal.jpg",
    "profile_image_url_https": "https://pbs.twimg.com/profile_images/871084233292267520/_esWF_cy_normal.jpg",
    "profile_banner_url": "https://pbs.twimg.com/profile_banners/1501772856/1477701342",
    "profile_link_color": "1DA1F2",
    "profile_sidebar_border_color": "C0DEED",
    "profile_sidebar_fill_color": "DDEEF6",
    "profile_text_color": "333333",
    "profile_use_background_image": true,
    "has_extended_profile": true,
    "default_profile": true,
    "default_profile_image": false,
    "has_custom_timelines": false,
    "can_media_tag": false,
    "followed_by": false,
    "following": false,
    "follow_request_sent": false,
    "notifications": false,
    "business_profile_state": "none",
    "translator_type": "none"
}