{
    "id": 2831645610,
    "id_str": "2831645610",
    "name": "\u30e4\u30cf\u30fc",
    "screen_name": "yaha_cuchi",
    "location": "\u6d77\u6d5c\u5e55\u5f35\u30c8\u30a4\u30ec",
    "description": "\u3077\u3088\u30af\u30a8AC\u304a\u75b2\u308c\u69d8(\u661f\u5927)\nRWBY\u597d\u304d\n\u30b7\u30e3\u30c9\u30d0AA1\nCHUNITHM13.30\n\u30c4\u30e0\u30c4\u30e0\n\u8155\u3054\u307c\u3046\nARMS 10\n\u30eb\u30b7\u30d5\u30a7\u30eb\u306f\u5815\u5929\u3057\u3066\u3082\u30cf\u30fc\u30c8\u3060\u3063\u305f\u3002",
    "url": "https://t.co/UunNpXZxHD",
    "entities": {
        "url": {
            "urls": [
                {
                    "url": "https://t.co/UunNpXZxHD",
                    "expanded_url": "http://twpf.jp/yaha_cuchi",
                    "display_url": "twpf.jp/yaha_cuchi",
                    "indices": [
                        0,
                        23
                    ]
                }
            ]
        },
        "description": {
            "urls": []
        }
    },
    "protected": false,
    "followers_count": 628,
    "fast_followers_count": 0,
    "normal_followers_count": 628,
    "friends_count": 1428,
    "listed_count": 8,
    "created_at": "Thu Sep 25 11:54:01 +0000 2014",
    "favourites_count": 3246,
    "utc_offset": -25200,
    "time_zone": "Pacific Time (US & Canada)",
    "geo_enabled": false,
    "verified": false,
    "statuses_count": 8484,
    "media_count": 1760,
    "lang": "ja",
    "status": {
        "created_at": "Wed Jul 19 22:46:26 +0000 2017",
        "id": 887805861447442433,
        "id_str": "887805861447442433",
        "text": "Twitter\u306e\u540d\u524d\u306b\u2606\u00a7\u03a3\u0e05\u03c9*\u30a8\u221eA\u00dc\u1ee6\u1ecf\u30ed\u1e85\uffe6\u06a1_\u03d6\u0e07\u0e07\u270c\u270c\u0648\u0669\u261d\u261e\u03c3\u03a3\u5f61\u24df\u24e4\u24e2\u24de\u24e0\u24e9\uffe1\uffe0\u332b\u3323\u3327\u3357\u334a\u334a\u3326\u3303\u3303\u044b\u0446\u0445\u0444\u043c\u0442\u0424\u0422\u041a\u2665\u2663\u260e\u2122\u00bf\u8a18\u53f7\u4f7f\u3046\u4eba\u3042\u307e\u308a\u597d\u304d\u3067\u306a\u3044",
        "truncated": false,
        "entities": {
            "hashtags": [],
            "symbols": [],
            "user_mentions": [],
            "urls": []
        },
        "source": "<a href=\"http://twitter.com/download/android\" rel=\"nofollow\">Twitter for Android</a>",
        "in_reply_to_status_id": null,
        "in_reply_to_status_id_str": null,
        "in_reply_to_user_id": null,
        "in_reply_to_user_id_str": null,
        "in_reply_to_screen_name": null,
        "geo": null,
        "coordinates": null,
        "place": null,
        "contributors": null,
        "is_quote_status": false,
        "retweet_count": 0,
        "favorite_count": 0,
        "favorited": false,
        "retweeted": false,
        "lang": "ja",
        "supplemental_language": null
    },
    "contributors_enabled": false,
    "is_translator": false,
    "is_translation_enabled": false,
    "profile_background_color": "000000",
    "profile_background_image_url": "http://abs.twimg.com/images/themes/theme1/bg.png",
    "profile_background_image_url_https": "https://abs.twimg.com/images/themes/theme1/bg.png",
    "profile_background_tile": false,
    "profile_image_url": "http://pbs.twimg.com/profile_images/881870218640842754/H7rB62ga_normal.jpg",
    "profile_image_url_https": "https://pbs.twimg.com/profile_images/881870218640842754/H7rB62ga_normal.jpg",
    "profile_banner_url": "https://pbs.twimg.com/profile_banners/2831645610/1500380466",
    "profile_link_color": "DD2E44",
    "profile_sidebar_border_color": "000000",
    "profile_sidebar_fill_color": "000000",
    "profile_text_color": "000000",
    "profile_use_background_image": false,
    "has_extended_profile": true,
    "default_profile": false,
    "default_profile_image": false,
    "has_custom_timelines": true,
    "can_media_tag": false,
    "followed_by": false,
    "following": false,
    "follow_request_sent": false,
    "notifications": false,
    "business_profile_state": "none",
    "translator_type": "none"
}