{
    "id": 823070181584814080,
    "id_str": "823070181584814080",
    "name": "\ud83c\udf3e\u3075\u30fc\u306f20\u300121\u65e5\u3068\u4e0d\u5728\u306a\u306e\u3060\u3088\ud83c\udf3e",
    "screen_name": "fu_1023LOVEYGN",
    "location": "\u7e54\u7530\u6cbc",
    "description": "\u7f8e\u5c11\u5e74\u63a2\u5075\u56e3\u3001\u5200\u5263\u4e71\u821e\u3001\u7d42\u308f\u308a\u306e\u30bb\u30e9\u30d5\u3001\u30d2\u30ed\u30a2\u30ab\u3001\u622f\u8a00\u30fb\u4eba\u9593\u30b7\u30ea\u30fc\u30ba\u300115\u2193\u306e\u5922\u8150\u5973\u5b50\u3002\u304a\u7c73\u63a8\u3057\u3066\u307e\u3059\u3002\u7d75\u3092\u66f8\u3044\u3066\u307e\u3059\u3002 \u81ea\u91cd\u3057\u306a\u3044\uff06\u65e5\u5e38\u30c4\u30a4\u591a\u3081\u3002\u304a\u984c\u7bb1https://t.co/jibMK69Lth\u30a2\u30a4\u30b3\u30f3\u306f\u304d\u3044\uff08@kiiiic)\u3068\u5408\u4f5c\u3002\u30d5\u30a1\u30dc\u7206\u9b54\u3002\uff03\u304a\u7c73\u7f8e\u5473\u3057\u3044\u3075\u30fc\u306e\u30e1\u30e2",
    "url": "https://t.co/TXwM1KhO6E",
    "entities": {
        "url": {
            "urls": [
                {
                    "url": "https://t.co/TXwM1KhO6E",
                    "expanded_url": "http://twpf.jp/fu_1023LOVEYGN",
                    "display_url": "twpf.jp/fu_1023LOVEYGN",
                    "indices": [
                        0,
                        23
                    ]
                }
            ]
        },
        "description": {
            "urls": [
                {
                    "url": "https://t.co/jibMK69Lth",
                    "expanded_url": "https://odaibako.net/u/fu_1023LOVEYGN",
                    "display_url": "odaibako.net/u/fu_1023LOVEY\u2026",
                    "indices": [
                        77,
                        100
                    ]
                }
            ]
        }
    },
    "protected": false,
    "followers_count": 211,
    "fast_followers_count": 0,
    "normal_followers_count": 211,
    "friends_count": 202,
    "listed_count": 27,
    "created_at": "Sun Jan 22 07:29:58 +0000 2017",
    "favourites_count": 11185,
    "utc_offset": -25200,
    "time_zone": "Pacific Time (US & Canada)",
    "geo_enabled": false,
    "verified": false,
    "statuses_count": 9222,
    "media_count": 110,
    "lang": "ja",
    "status": {
        "created_at": "Wed Jul 19 22:28:07 +0000 2017",
        "id": 887801249285906436,
        "id_str": "887801249285906436",
        "text": "\u884c\u3063\u3066\u304f\u308b\u306d",
        "truncated": false,
        "entities": {
            "hashtags": [],
            "symbols": [],
            "user_mentions": [],
            "urls": []
        },
        "source": "<a href=\"http://twitter.com\" rel=\"nofollow\">Twitter Web Client</a>",
        "in_reply_to_status_id": null,
        "in_reply_to_status_id_str": null,
        "in_reply_to_user_id": null,
        "in_reply_to_user_id_str": null,
        "in_reply_to_screen_name": null,
        "geo": null,
        "coordinates": null,
        "place": null,
        "contributors": null,
        "is_quote_status": false,
        "retweet_count": 0,
        "favorite_count": 1,
        "favorited": false,
        "retweeted": false,
        "lang": "ja",
        "supplemental_language": null
    },
    "contributors_enabled": false,
    "is_translator": false,
    "is_translation_enabled": false,
    "profile_background_color": "000000",
    "profile_background_image_url": "http://abs.twimg.com/images/themes/theme1/bg.png",
    "profile_background_image_url_https": "https://abs.twimg.com/images/themes/theme1/bg.png",
    "profile_background_tile": false,
    "profile_image_url": "http://pbs.twimg.com/profile_images/882926857745608705/jmikazy0_normal.jpg",
    "profile_image_url_https": "https://pbs.twimg.com/profile_images/882926857745608705/jmikazy0_normal.jpg",
    "profile_banner_url": "https://pbs.twimg.com/profile_banners/823070181584814080/1490284709",
    "profile_link_color": "E81C4F",
    "profile_sidebar_border_color": "000000",
    "profile_sidebar_fill_color": "000000",
    "profile_text_color": "000000",
    "profile_use_background_image": false,
    "has_extended_profile": true,
    "default_profile": false,
    "default_profile_image": false,
    "has_custom_timelines": true,
    "can_media_tag": false,
    "followed_by": false,
    "following": false,
    "follow_request_sent": false,
    "notifications": false,
    "business_profile_state": "none",
    "translator_type": "none"
}