{
    "id": 3349197314,
    "id_str": "3349197314",
    "name": "H a r u  \u5bae\u57ce\u53c2\u6226",
    "screen_name": "hr__v6",
    "location": "",
    "description": "................................................................................... 6\u4eba\u306e\uff75\uff7c\uff9e\uff7b\uff9d \u3092\u611b\u3067\u308bJK \ud83c\udf31\u201c@sn_V6_mk\u201d",
    "url": "https://t.co/7sPvNN0CLU",
    "entities": {
        "url": {
            "urls": [
                {
                    "url": "https://t.co/7sPvNN0CLU",
                    "expanded_url": "http://twpf.jp/hr__v6",
                    "display_url": "twpf.jp/hr__v6",
                    "indices": [
                        0,
                        23
                    ]
                }
            ]
        },
        "description": {
            "urls": []
        }
    },
    "protected": false,
    "followers_count": 631,
    "fast_followers_count": 0,
    "normal_followers_count": 631,
    "friends_count": 203,
    "listed_count": 8,
    "created_at": "Wed Aug 26 14:20:43 +0000 2015",
    "favourites_count": 56,
    "utc_offset": null,
    "time_zone": null,
    "geo_enabled": true,
    "verified": false,
    "statuses_count": 8694,
    "media_count": 227,
    "lang": "ja",
    "status": {
        "created_at": "Thu Jul 13 13:56:07 +0000 2017",
        "id": 885498075791335424,
        "id_str": "885498075791335424",
        "text": "RT @1997TBS2008: \u9577\u91ce\u304f\u3093\u304c\u72a0\u7272\u306b\u306a\u308a\u307e\u3057\u305f https://t.co/Gfr62ImW0N",
        "truncated": false,
        "entities": {
            "hashtags": [],
            "symbols": [],
            "user_mentions": [
                {
                    "screen_name": "1997TBS2008",
                    "name": "\u307e\u3053\u3068",
                    "id": 2870400955,
                    "id_str": "2870400955",
                    "indices": [
                        3,
                        15
                    ]
                }
            ],
            "urls": [],
            "media": [
                {
                    "id": 885496887452631041,
                    "id_str": "885496887452631041",
                    "indices": [
                        31,
                        54
                    ],
                    "media_url": "http://pbs.twimg.com/media/DEnqukJUAAEtERW.jpg",
                    "media_url_https": "https://pbs.twimg.com/media/DEnqukJUAAEtERW.jpg",
                    "url": "https://t.co/Gfr62ImW0N",
                    "display_url": "pic.twitter.com/Gfr62ImW0N",
                    "expanded_url": "https://twitter.com/1997TBS2008/status/885496893681287169/photo/1",
                    "type": "photo",
                    "sizes": {
                        "small": {
                            "w": 600,
                            "h": 337,
                            "resize": "fit"
                        },
                        "large": {
                            "w": 600,
                            "h": 337,
                            "resize": "fit"
                        },
                        "medium": {
                            "w": 600,
                            "h": 337,
                            "resize": "fit"
                        },
                        "thumb": {
                            "w": 150,
                            "h": 150,
                            "resize": "crop"
                        }
                    },
                    "source_status_id": 885496893681287169,
                    "source_status_id_str": "885496893681287169",
                    "source_user_id": 2870400955,
                    "source_user_id_str": "2870400955",
                    "features": {
                        "small": {
                            "faces": [
                                {
                                    "x": 64,
                                    "y": 8,
                                    "h": 39,
                                    "w": 39
                                }
                            ]
                        },
                        "large": {
                            "faces": [
                                {
                                    "x": 64,
                                    "y": 8,
                                    "h": 39,
                                    "w": 39
                                }
                            ]
                        },
                        "medium": {
                            "faces": [
                                {
                                    "x": 64,
                                    "y": 8,
                                    "h": 39,
                                    "w": 39
                                }
                            ]
                        },
                        "orig": {
                            "faces": [
                                {
                                    "x": 64,
                                    "y": 8,
                                    "h": 39,
                                    "w": 39
                                }
                            ]
                        }
                    }
                }
            ]
        },
        "extended_entities": {
            "media": [
                {
                    "id": 885496887452631041,
                    "id_str": "885496887452631041",
                    "indices": [
                        31,
                        54
                    ],
                    "media_url": "http://pbs.twimg.com/media/DEnqukJUAAEtERW.jpg",
                    "media_url_https": "https://pbs.twimg.com/media/DEnqukJUAAEtERW.jpg",
                    "url": "https://t.co/Gfr62ImW0N",
                    "display_url": "pic.twitter.com/Gfr62ImW0N",
                    "expanded_url": "https://twitter.com/1997TBS2008/status/885496893681287169/photo/1",
                    "type": "photo",
                    "sizes": {
                        "small": {
                            "w": 600,
                            "h": 337,
                            "resize": "fit"
                        },
                        "large": {
                            "w": 600,
                            "h": 337,
                            "resize": "fit"
                        },
                        "medium": {
                            "w": 600,
                            "h": 337,
                            "resize": "fit"
                        },
                        "thumb": {
                            "w": 150,
                            "h": 150,
                            "resize": "crop"
                        }
                    },
                    "source_status_id": 885496893681287169,
                    "source_status_id_str": "885496893681287169",
                    "source_user_id": 2870400955,
                    "source_user_id_str": "2870400955",
                    "features": {
                        "small": {
                            "faces": [
                                {
                                    "x": 64,
                                    "y": 8,
                                    "h": 39,
                                    "w": 39
                                }
                            ]
                        },
                        "large": {
                            "faces": [
                                {
                                    "x": 64,
                                    "y": 8,
                                    "h": 39,
                                    "w": 39
                                }
                            ]
                        },
                        "medium": {
                            "faces": [
                                {
                                    "x": 64,
                                    "y": 8,
                                    "h": 39,
                                    "w": 39
                                }
                            ]
                        },
                        "orig": {
                            "faces": [
                                {
                                    "x": 64,
                                    "y": 8,
                                    "h": 39,
                                    "w": 39
                                }
                            ]
                        }
                    }
                },
                {
                    "id": 885496887448485888,
                    "id_str": "885496887448485888",
                    "indices": [
                        31,
                        54
                    ],
                    "media_url": "http://pbs.twimg.com/media/DEnqukIUwAAnuvs.jpg",
                    "media_url_https": "https://pbs.twimg.com/media/DEnqukIUwAAnuvs.jpg",
                    "url": "https://t.co/Gfr62ImW0N",
                    "display_url": "pic.twitter.com/Gfr62ImW0N",
                    "expanded_url": "https://twitter.com/1997TBS2008/status/885496893681287169/photo/1",
                    "type": "photo",
                    "sizes": {
                        "thumb": {
                            "w": 150,
                            "h": 150,
                            "resize": "crop"
                        },
                        "large": {
                            "w": 600,
                            "h": 337,
                            "resize": "fit"
                        },
                        "medium": {
                            "w": 600,
                            "h": 337,
                            "resize": "fit"
                        },
                        "small": {
                            "w": 600,
                            "h": 337,
                            "resize": "fit"
                        }
                    },
                    "source_status_id": 885496893681287169,
                    "source_status_id_str": "885496893681287169",
                    "source_user_id": 2870400955,
                    "source_user_id_str": "2870400955",
                    "features": {
                        "large": {
                            "faces": [
                                {
                                    "x": 76,
                                    "y": 5,
                                    "h": 38,
                                    "w": 38
                                },
                                {
                                    "x": 387,
                                    "y": 93,
                                    "h": 53,
                                    "w": 53
                                },
                                {
                                    "x": 40,
                                    "y": 161,
                                    "h": 57,
                                    "w": 57
                                }
                            ]
                        },
                        "orig": {
                            "faces": [
                                {
                                    "x": 76,
                                    "y": 5,
                                    "h": 38,
                                    "w": 38
                                },
                                {
                                    "x": 387,
                                    "y": 93,
                                    "h": 53,
                                    "w": 53
                                },
                                {
                                    "x": 40,
                                    "y": 161,
                                    "h": 57,
                                    "w": 57
                                }
                            ]
                        },
                        "medium": {
                            "faces": [
                                {
                                    "x": 76,
                                    "y": 5,
                                    "h": 38,
                                    "w": 38
                                },
                                {
                                    "x": 387,
                                    "y": 93,
                                    "h": 53,
                                    "w": 53
                                },
                                {
                                    "x": 40,
                                    "y": 161,
                                    "h": 57,
                                    "w": 57
                                }
                            ]
                        },
                        "small": {
                            "faces": [
                                {
                                    "x": 76,
                                    "y": 5,
                                    "h": 38,
                                    "w": 38
                                },
                                {
                                    "x": 387,
                                    "y": 93,
                                    "h": 53,
                                    "w": 53
                                },
                                {
                                    "x": 40,
                                    "y": 161,
                                    "h": 57,
                                    "w": 57
                                }
                            ]
                        }
                    }
                },
                {
                    "id": 885496887456841728,
                    "id_str": "885496887456841728",
                    "indices": [
                        31,
                        54
                    ],
                    "media_url": "http://pbs.twimg.com/media/DEnqukKUQAA8lVD.jpg",
                    "media_url_https": "https://pbs.twimg.com/media/DEnqukKUQAA8lVD.jpg",
                    "url": "https://t.co/Gfr62ImW0N",
                    "display_url": "pic.twitter.com/Gfr62ImW0N",
                    "expanded_url": "https://twitter.com/1997TBS2008/status/885496893681287169/photo/1",
                    "type": "photo",
                    "sizes": {
                        "thumb": {
                            "w": 150,
                            "h": 150,
                            "resize": "crop"
                        },
                        "small": {
                            "w": 580,
                            "h": 326,
                            "resize": "fit"
                        },
                        "large": {
                            "w": 580,
                            "h": 326,
                            "resize": "fit"
                        },
                        "medium": {
                            "w": 580,
                            "h": 326,
                            "resize": "fit"
                        }
                    },
                    "source_status_id": 885496893681287169,
                    "source_status_id_str": "885496893681287169",
                    "source_user_id": 2870400955,
                    "source_user_id_str": "2870400955",
                    "features": {
                        "orig": {
                            "faces": [
                                {
                                    "x": 39,
                                    "y": 148,
                                    "h": 57,
                                    "w": 57
                                },
                                {
                                    "x": 368,
                                    "y": 65,
                                    "h": 64,
                                    "w": 64
                                }
                            ]
                        },
                        "small": {
                            "faces": [
                                {
                                    "x": 39,
                                    "y": 148,
                                    "h": 57,
                                    "w": 57
                                },
                                {
                                    "x": 368,
                                    "y": 65,
                                    "h": 64,
                                    "w": 64
                                }
                            ]
                        },
                        "large": {
                            "faces": [
                                {
                                    "x": 39,
                                    "y": 148,
                                    "h": 57,
                                    "w": 57
                                },
                                {
                                    "x": 368,
                                    "y": 65,
                                    "h": 64,
                                    "w": 64
                                }
                            ]
                        },
                        "medium": {
                            "faces": [
                                {
                                    "x": 39,
                                    "y": 148,
                                    "h": 57,
                                    "w": 57
                                },
                                {
                                    "x": 368,
                                    "y": 65,
                                    "h": 64,
                                    "w": 64
                                }
                            ]
                        }
                    }
                },
                {
                    "id": 885496887456833536,
                    "id_str": "885496887456833536",
                    "indices": [
                        31,
                        54
                    ],
                    "media_url": "http://pbs.twimg.com/media/DEnqukKUIAA2LDf.jpg",
                    "media_url_https": "https://pbs.twimg.com/media/DEnqukKUIAA2LDf.jpg",
                    "url": "https://t.co/Gfr62ImW0N",
                    "display_url": "pic.twitter.com/Gfr62ImW0N",
                    "expanded_url": "https://twitter.com/1997TBS2008/status/885496893681287169/photo/1",
                    "type": "photo",
                    "sizes": {
                        "large": {
                            "w": 600,
                            "h": 337,
                            "resize": "fit"
                        },
                        "thumb": {
                            "w": 150,
                            "h": 150,
                            "resize": "crop"
                        },
                        "medium": {
                            "w": 600,
                            "h": 337,
                            "resize": "fit"
                        },
                        "small": {
                            "w": 600,
                            "h": 337,
                            "resize": "fit"
                        }
                    },
                    "source_status_id": 885496893681287169,
                    "source_status_id_str": "885496893681287169",
                    "source_user_id": 2870400955,
                    "source_user_id_str": "2870400955",
                    "features": {
                        "large": {
                            "faces": [
                                {
                                    "x": 70,
                                    "y": 2,
                                    "h": 35,
                                    "w": 35
                                },
                                {
                                    "x": 5,
                                    "y": 5,
                                    "h": 39,
                                    "w": 39
                                },
                                {
                                    "x": 30,
                                    "y": 164,
                                    "h": 58,
                                    "w": 58
                                },
                                {
                                    "x": 227,
                                    "y": 58,
                                    "h": 144,
                                    "w": 144
                                }
                            ]
                        },
                        "orig": {
                            "faces": [
                                {
                                    "x": 70,
                                    "y": 2,
                                    "h": 35,
                                    "w": 35
                                },
                                {
                                    "x": 5,
                                    "y": 5,
                                    "h": 39,
                                    "w": 39
                                },
                                {
                                    "x": 30,
                                    "y": 164,
                                    "h": 58,
                                    "w": 58
                                },
                                {
                                    "x": 227,
                                    "y": 58,
                                    "h": 144,
                                    "w": 144
                                }
                            ]
                        },
                        "medium": {
                            "faces": [
                                {
                                    "x": 70,
                                    "y": 2,
                                    "h": 35,
                                    "w": 35
                                },
                                {
                                    "x": 5,
                                    "y": 5,
                                    "h": 39,
                                    "w": 39
                                },
                                {
                                    "x": 30,
                                    "y": 164,
                                    "h": 58,
                                    "w": 58
                                },
                                {
                                    "x": 227,
                                    "y": 58,
                                    "h": 144,
                                    "w": 144
                                }
                            ]
                        },
                        "small": {
                            "faces": [
                                {
                                    "x": 70,
                                    "y": 2,
                                    "h": 35,
                                    "w": 35
                                },
                                {
                                    "x": 5,
                                    "y": 5,
                                    "h": 39,
                                    "w": 39
                                },
                                {
                                    "x": 30,
                                    "y": 164,
                                    "h": 58,
                                    "w": 58
                                },
                                {
                                    "x": 227,
                                    "y": 58,
                                    "h": 144,
                                    "w": 144
                                }
                            ]
                        }
                    }
                }
            ]
        },
        "source": "<a href=\"http://twitter.com/download/iphone\" rel=\"nofollow\">Twitter for iPhone</a>",
        "in_reply_to_status_id": null,
        "in_reply_to_status_id_str": null,
        "in_reply_to_user_id": null,
        "in_reply_to_user_id_str": null,
        "in_reply_to_screen_name": null,
        "geo": null,
        "coordinates": null,
        "place": null,
        "contributors": null,
        "retweeted_status": {
            "created_at": "Thu Jul 13 13:51:25 +0000 2017",
            "id": 885496893681287169,
            "id_str": "885496893681287169",
            "text": "\u9577\u91ce\u304f\u3093\u304c\u72a0\u7272\u306b\u306a\u308a\u307e\u3057\u305f https://t.co/Gfr62ImW0N",
            "truncated": false,
            "entities": {
                "hashtags": [],
                "symbols": [],
                "user_mentions": [],
                "urls": [],
                "media": [
                    {
                        "id": 885496887452631041,
                        "id_str": "885496887452631041",
                        "indices": [
                            14,
                            37
                        ],
                        "media_url": "http://pbs.twimg.com/media/DEnqukJUAAEtERW.jpg",
                        "media_url_https": "https://pbs.twimg.com/media/DEnqukJUAAEtERW.jpg",
                        "url": "https://t.co/Gfr62ImW0N",
                        "display_url": "pic.twitter.com/Gfr62ImW0N",
                        "expanded_url": "https://twitter.com/1997TBS2008/status/885496893681287169/photo/1",
                        "type": "photo",
                        "sizes": {
                            "small": {
                                "w": 600,
                                "h": 337,
                                "resize": "fit"
                            },
                            "large": {
                                "w": 600,
                                "h": 337,
                                "resize": "fit"
                            },
                            "medium": {
                                "w": 600,
                                "h": 337,
                                "resize": "fit"
                            },
                            "thumb": {
                                "w": 150,
                                "h": 150,
                                "resize": "crop"
                            }
                        },
                        "features": {
                            "small": {
                                "faces": [
                                    {
                                        "x": 64,
                                        "y": 8,
                                        "h": 39,
                                        "w": 39
                                    }
                                ]
                            },
                            "large": {
                                "faces": [
                                    {
                                        "x": 64,
                                        "y": 8,
                                        "h": 39,
                                        "w": 39
                                    }
                                ]
                            },
                            "medium": {
                                "faces": [
                                    {
                                        "x": 64,
                                        "y": 8,
                                        "h": 39,
                                        "w": 39
                                    }
                                ]
                            },
                            "orig": {
                                "faces": [
                                    {
                                        "x": 64,
                                        "y": 8,
                                        "h": 39,
                                        "w": 39
                                    }
                                ]
                            }
                        }
                    }
                ]
            },
            "extended_entities": {
                "media": [
                    {
                        "id": 885496887452631041,
                        "id_str": "885496887452631041",
                        "indices": [
                            14,
                            37
                        ],
                        "media_url": "http://pbs.twimg.com/media/DEnqukJUAAEtERW.jpg",
                        "media_url_https": "https://pbs.twimg.com/media/DEnqukJUAAEtERW.jpg",
                        "url": "https://t.co/Gfr62ImW0N",
                        "display_url": "pic.twitter.com/Gfr62ImW0N",
                        "expanded_url": "https://twitter.com/1997TBS2008/status/885496893681287169/photo/1",
                        "type": "photo",
                        "sizes": {
                            "small": {
                                "w": 600,
                                "h": 337,
                                "resize": "fit"
                            },
                            "large": {
                                "w": 600,
                                "h": 337,
                                "resize": "fit"
                            },
                            "medium": {
                                "w": 600,
                                "h": 337,
                                "resize": "fit"
                            },
                            "thumb": {
                                "w": 150,
                                "h": 150,
                                "resize": "crop"
                            }
                        },
                        "features": {
                            "small": {
                                "faces": [
                                    {
                                        "x": 64,
                                        "y": 8,
                                        "h": 39,
                                        "w": 39
                                    }
                                ]
                            },
                            "large": {
                                "faces": [
                                    {
                                        "x": 64,
                                        "y": 8,
                                        "h": 39,
                                        "w": 39
                                    }
                                ]
                            },
                            "medium": {
                                "faces": [
                                    {
                                        "x": 64,
                                        "y": 8,
                                        "h": 39,
                                        "w": 39
                                    }
                                ]
                            },
                            "orig": {
                                "faces": [
                                    {
                                        "x": 64,
                                        "y": 8,
                                        "h": 39,
                                        "w": 39
                                    }
                                ]
                            }
                        }
                    },
                    {
                        "id": 885496887448485888,
                        "id_str": "885496887448485888",
                        "indices": [
                            14,
                            37
                        ],
                        "media_url": "http://pbs.twimg.com/media/DEnqukIUwAAnuvs.jpg",
                        "media_url_https": "https://pbs.twimg.com/media/DEnqukIUwAAnuvs.jpg",
                        "url": "https://t.co/Gfr62ImW0N",
                        "display_url": "pic.twitter.com/Gfr62ImW0N",
                        "expanded_url": "https://twitter.com/1997TBS2008/status/885496893681287169/photo/1",
                        "type": "photo",
                        "sizes": {
                            "thumb": {
                                "w": 150,
                                "h": 150,
                                "resize": "crop"
                            },
                            "large": {
                                "w": 600,
                                "h": 337,
                                "resize": "fit"
                            },
                            "medium": {
                                "w": 600,
                                "h": 337,
                                "resize": "fit"
                            },
                            "small": {
                                "w": 600,
                                "h": 337,
                                "resize": "fit"
                            }
                        },
                        "features": {
                            "large": {
                                "faces": [
                                    {
                                        "x": 76,
                                        "y": 5,
                                        "h": 38,
                                        "w": 38
                                    },
                                    {
                                        "x": 387,
                                        "y": 93,
                                        "h": 53,
                                        "w": 53
                                    },
                                    {
                                        "x": 40,
                                        "y": 161,
                                        "h": 57,
                                        "w": 57
                                    }
                                ]
                            },
                            "orig": {
                                "faces": [
                                    {
                                        "x": 76,
                                        "y": 5,
                                        "h": 38,
                                        "w": 38
                                    },
                                    {
                                        "x": 387,
                                        "y": 93,
                                        "h": 53,
                                        "w": 53
                                    },
                                    {
                                        "x": 40,
                                        "y": 161,
                                        "h": 57,
                                        "w": 57
                                    }
                                ]
                            },
                            "medium": {
                                "faces": [
                                    {
                                        "x": 76,
                                        "y": 5,
                                        "h": 38,
                                        "w": 38
                                    },
                                    {
                                        "x": 387,
                                        "y": 93,
                                        "h": 53,
                                        "w": 53
                                    },
                                    {
                                        "x": 40,
                                        "y": 161,
                                        "h": 57,
                                        "w": 57
                                    }
                                ]
                            },
                            "small": {
                                "faces": [
                                    {
                                        "x": 76,
                                        "y": 5,
                                        "h": 38,
                                        "w": 38
                                    },
                                    {
                                        "x": 387,
                                        "y": 93,
                                        "h": 53,
                                        "w": 53
                                    },
                                    {
                                        "x": 40,
                                        "y": 161,
                                        "h": 57,
                                        "w": 57
                                    }
                                ]
                            }
                        }
                    },
                    {
                        "id": 885496887456841728,
                        "id_str": "885496887456841728",
                        "indices": [
                            14,
                            37
                        ],
                        "media_url": "http://pbs.twimg.com/media/DEnqukKUQAA8lVD.jpg",
                        "media_url_https": "https://pbs.twimg.com/media/DEnqukKUQAA8lVD.jpg",
                        "url": "https://t.co/Gfr62ImW0N",
                        "display_url": "pic.twitter.com/Gfr62ImW0N",
                        "expanded_url": "https://twitter.com/1997TBS2008/status/885496893681287169/photo/1",
                        "type": "photo",
                        "sizes": {
                            "thumb": {
                                "w": 150,
                                "h": 150,
                                "resize": "crop"
                            },
                            "small": {
                                "w": 580,
                                "h": 326,
                                "resize": "fit"
                            },
                            "large": {
                                "w": 580,
                                "h": 326,
                                "resize": "fit"
                            },
                            "medium": {
                                "w": 580,
                                "h": 326,
                                "resize": "fit"
                            }
                        },
                        "features": {
                            "orig": {
                                "faces": [
                                    {
                                        "x": 39,
                                        "y": 148,
                                        "h": 57,
                                        "w": 57
                                    },
                                    {
                                        "x": 368,
                                        "y": 65,
                                        "h": 64,
                                        "w": 64
                                    }
                                ]
                            },
                            "small": {
                                "faces": [
                                    {
                                        "x": 39,
                                        "y": 148,
                                        "h": 57,
                                        "w": 57
                                    },
                                    {
                                        "x": 368,
                                        "y": 65,
                                        "h": 64,
                                        "w": 64
                                    }
                                ]
                            },
                            "large": {
                                "faces": [
                                    {
                                        "x": 39,
                                        "y": 148,
                                        "h": 57,
                                        "w": 57
                                    },
                                    {
                                        "x": 368,
                                        "y": 65,
                                        "h": 64,
                                        "w": 64
                                    }
                                ]
                            },
                            "medium": {
                                "faces": [
                                    {
                                        "x": 39,
                                        "y": 148,
                                        "h": 57,
                                        "w": 57
                                    },
                                    {
                                        "x": 368,
                                        "y": 65,
                                        "h": 64,
                                        "w": 64
                                    }
                                ]
                            }
                        }
                    },
                    {
                        "id": 885496887456833536,
                        "id_str": "885496887456833536",
                        "indices": [
                            14,
                            37
                        ],
                        "media_url": "http://pbs.twimg.com/media/DEnqukKUIAA2LDf.jpg",
                        "media_url_https": "https://pbs.twimg.com/media/DEnqukKUIAA2LDf.jpg",
                        "url": "https://t.co/Gfr62ImW0N",
                        "display_url": "pic.twitter.com/Gfr62ImW0N",
                        "expanded_url": "https://twitter.com/1997TBS2008/status/885496893681287169/photo/1",
                        "type": "photo",
                        "sizes": {
                            "large": {
                                "w": 600,
                                "h": 337,
                                "resize": "fit"
                            },
                            "thumb": {
                                "w": 150,
                                "h": 150,
                                "resize": "crop"
                            },
                            "medium": {
                                "w": 600,
                                "h": 337,
                                "resize": "fit"
                            },
                            "small": {
                                "w": 600,
                                "h": 337,
                                "resize": "fit"
                            }
                        },
                        "features": {
                            "large": {
                                "faces": [
                                    {
                                        "x": 70,
                                        "y": 2,
                                        "h": 35,
                                        "w": 35
                                    },
                                    {
                                        "x": 5,
                                        "y": 5,
                                        "h": 39,
                                        "w": 39
                                    },
                                    {
                                        "x": 30,
                                        "y": 164,
                                        "h": 58,
                                        "w": 58
                                    },
                                    {
                                        "x": 227,
                                        "y": 58,
                                        "h": 144,
                                        "w": 144
                                    }
                                ]
                            },
                            "orig": {
                                "faces": [
                                    {
                                        "x": 70,
                                        "y": 2,
                                        "h": 35,
                                        "w": 35
                                    },
                                    {
                                        "x": 5,
                                        "y": 5,
                                        "h": 39,
                                        "w": 39
                                    },
                                    {
                                        "x": 30,
                                        "y": 164,
                                        "h": 58,
                                        "w": 58
                                    },
                                    {
                                        "x": 227,
                                        "y": 58,
                                        "h": 144,
                                        "w": 144
                                    }
                                ]
                            },
                            "medium": {
                                "faces": [
                                    {
                                        "x": 70,
                                        "y": 2,
                                        "h": 35,
                                        "w": 35
                                    },
                                    {
                                        "x": 5,
                                        "y": 5,
                                        "h": 39,
                                        "w": 39
                                    },
                                    {
                                        "x": 30,
                                        "y": 164,
                                        "h": 58,
                                        "w": 58
                                    },
                                    {
                                        "x": 227,
                                        "y": 58,
                                        "h": 144,
                                        "w": 144
                                    }
                                ]
                            },
                            "small": {
                                "faces": [
                                    {
                                        "x": 70,
                                        "y": 2,
                                        "h": 35,
                                        "w": 35
                                    },
                                    {
                                        "x": 5,
                                        "y": 5,
                                        "h": 39,
                                        "w": 39
                                    },
                                    {
                                        "x": 30,
                                        "y": 164,
                                        "h": 58,
                                        "w": 58
                                    },
                                    {
                                        "x": 227,
                                        "y": 58,
                                        "h": 144,
                                        "w": 144
                                    }
                                ]
                            }
                        }
                    }
                ]
            },
            "source": "<a href=\"http://twitter.com/download/iphone\" rel=\"nofollow\">Twitter for iPhone</a>",
            "in_reply_to_status_id": null,
            "in_reply_to_status_id_str": null,
            "in_reply_to_user_id": null,
            "in_reply_to_user_id_str": null,
            "in_reply_to_screen_name": null,
            "geo": null,
            "coordinates": null,
            "place": null,
            "contributors": null,
            "is_quote_status": false,
            "retweet_count": 222,
            "favorite_count": 839,
            "favorited": false,
            "retweeted": false,
            "possibly_sensitive": false,
            "lang": "ja",
            "supplemental_language": null
        },
        "is_quote_status": false,
        "retweet_count": 222,
        "favorite_count": 0,
        "favorited": false,
        "retweeted": false,
        "possibly_sensitive": false,
        "lang": "ja",
        "supplemental_language": null
    },
    "contributors_enabled": false,
    "is_translator": false,
    "is_translation_enabled": false,
    "profile_background_color": "C0DEED",
    "profile_background_image_url": "http://abs.twimg.com/images/themes/theme1/bg.png",
    "profile_background_image_url_https": "https://abs.twimg.com/images/themes/theme1/bg.png",
    "profile_background_tile": false,
    "profile_image_url": "http://pbs.twimg.com/profile_images/878949777768984576/v1lckNBq_normal.jpg",
    "profile_image_url_https": "https://pbs.twimg.com/profile_images/878949777768984576/v1lckNBq_normal.jpg",
    "profile_banner_url": "https://pbs.twimg.com/profile_banners/3349197314/1484409262",
    "profile_link_color": "1DA1F2",
    "profile_sidebar_border_color": "C0DEED",
    "profile_sidebar_fill_color": "DDEEF6",
    "profile_text_color": "333333",
    "profile_use_background_image": true,
    "has_extended_profile": false,
    "default_profile": true,
    "default_profile_image": false,
    "has_custom_timelines": false,
    "can_media_tag": false,
    "followed_by": false,
    "following": false,
    "follow_request_sent": false,
    "notifications": false,
    "business_profile_state": "none",
    "translator_type": "none"
}