{
    "id": 833028716426993664,
    "id_str": "833028716426993664",
    "name": "iroha@\u30b7\u30e3\u30c9\u30d0\ud83d\udc1f",
    "screen_name": "Nanairo07291",
    "location": "\u65e5\u672c",
    "description": "\u307c\u3061\u307c\u3061\u3084\u3063\u3066\u3044\u304d\u307e\u3059\uff01\nLiSA\u3061\u3083\u3093 \u5927\u539f\u6afb\u5b50\u3061\u3083\u3093 \u3057\u3057\u3083\u3082 \u30a4\u30c8\u30f2\u30ab\u30b7\n\n\u30d5\u30a3\u30c3\u30b7\u30e3\u30fc\u30ba \u306f\u3058\u3081\u3093 \u30b7\u30e3\u30c9\u30d0",
    "url": null,
    "entities": {
        "description": {
            "urls": []
        }
    },
    "protected": false,
    "followers_count": 261,
    "fast_followers_count": 0,
    "normal_followers_count": 261,
    "friends_count": 325,
    "listed_count": 1,
    "created_at": "Sat Feb 18 19:01:37 +0000 2017",
    "favourites_count": 341,
    "utc_offset": null,
    "time_zone": null,
    "geo_enabled": false,
    "verified": false,
    "statuses_count": 135,
    "media_count": 6,
    "lang": "ja",
    "status": {
        "created_at": "Mon May 08 11:47:27 +0000 2017",
        "id": 861548094978015233,
        "id_str": "861548094978015233",
        "text": "RT @trppyyy: \u304a\u3044B\u30e9\u30f3\u30af\u4ee5\u4e0b\u7121\u304f\u306a\u308b\u3089\u3057\u3044\u305e https://t.co/AzC4by1SZI",
        "truncated": false,
        "entities": {
            "hashtags": [],
            "symbols": [],
            "user_mentions": [
                {
                    "screen_name": "trppyyy",
                    "name": "\u3068\u308a",
                    "id": 795127952480473088,
                    "id_str": "795127952480473088",
                    "indices": [
                        3,
                        11
                    ]
                }
            ],
            "urls": [],
            "media": [
                {
                    "id": 861217311549571074,
                    "id_str": "861217311549571074",
                    "indices": [
                        30,
                        53
                    ],
                    "media_url": "http://pbs.twimg.com/media/C_OolPlUQAIAIP6.jpg",
                    "media_url_https": "https://pbs.twimg.com/media/C_OolPlUQAIAIP6.jpg",
                    "url": "https://t.co/AzC4by1SZI",
                    "display_url": "pic.twitter.com/AzC4by1SZI",
                    "expanded_url": "https://twitter.com/trppyyy/status/861217317434171392/photo/1",
                    "type": "photo",
                    "sizes": {
                        "large": {
                            "w": 600,
                            "h": 337,
                            "resize": "fit"
                        },
                        "small": {
                            "w": 600,
                            "h": 337,
                            "resize": "fit"
                        },
                        "medium": {
                            "w": 600,
                            "h": 337,
                            "resize": "fit"
                        },
                        "thumb": {
                            "w": 150,
                            "h": 150,
                            "resize": "crop"
                        }
                    },
                    "source_status_id": 861217317434171392,
                    "source_status_id_str": "861217317434171392",
                    "source_user_id": 795127952480473088,
                    "source_user_id_str": "795127952480473088",
                    "features": {
                        "large": {
                            "faces": []
                        },
                        "small": {
                            "faces": []
                        },
                        "medium": {
                            "faces": []
                        },
                        "orig": {
                            "faces": []
                        }
                    }
                }
            ]
        },
        "extended_entities": {
            "media": [
                {
                    "id": 861217311549571074,
                    "id_str": "861217311549571074",
                    "indices": [
                        30,
                        53
                    ],
                    "media_url": "http://pbs.twimg.com/media/C_OolPlUQAIAIP6.jpg",
                    "media_url_https": "https://pbs.twimg.com/media/C_OolPlUQAIAIP6.jpg",
                    "url": "https://t.co/AzC4by1SZI",
                    "display_url": "pic.twitter.com/AzC4by1SZI",
                    "expanded_url": "https://twitter.com/trppyyy/status/861217317434171392/photo/1",
                    "type": "photo",
                    "sizes": {
                        "large": {
                            "w": 600,
                            "h": 337,
                            "resize": "fit"
                        },
                        "small": {
                            "w": 600,
                            "h": 337,
                            "resize": "fit"
                        },
                        "medium": {
                            "w": 600,
                            "h": 337,
                            "resize": "fit"
                        },
                        "thumb": {
                            "w": 150,
                            "h": 150,
                            "resize": "crop"
                        }
                    },
                    "source_status_id": 861217317434171392,
                    "source_status_id_str": "861217317434171392",
                    "source_user_id": 795127952480473088,
                    "source_user_id_str": "795127952480473088",
                    "features": {
                        "large": {
                            "faces": []
                        },
                        "small": {
                            "faces": []
                        },
                        "medium": {
                            "faces": []
                        },
                        "orig": {
                            "faces": []
                        }
                    }
                }
            ]
        },
        "source": "<a href=\"http://twitter.com/download/android\" rel=\"nofollow\">Twitter for Android</a>",
        "in_reply_to_status_id": null,
        "in_reply_to_status_id_str": null,
        "in_reply_to_user_id": null,
        "in_reply_to_user_id_str": null,
        "in_reply_to_screen_name": null,
        "geo": null,
        "coordinates": null,
        "place": null,
        "contributors": null,
        "retweeted_status": {
            "created_at": "Sun May 07 13:53:03 +0000 2017",
            "id": 861217317434171392,
            "id_str": "861217317434171392",
            "text": "\u304a\u3044B\u30e9\u30f3\u30af\u4ee5\u4e0b\u7121\u304f\u306a\u308b\u3089\u3057\u3044\u305e https://t.co/AzC4by1SZI",
            "truncated": false,
            "entities": {
                "hashtags": [],
                "symbols": [],
                "user_mentions": [],
                "urls": [],
                "media": [
                    {
                        "id": 861217311549571074,
                        "id_str": "861217311549571074",
                        "indices": [
                            17,
                            40
                        ],
                        "media_url": "http://pbs.twimg.com/media/C_OolPlUQAIAIP6.jpg",
                        "media_url_https": "https://pbs.twimg.com/media/C_OolPlUQAIAIP6.jpg",
                        "url": "https://t.co/AzC4by1SZI",
                        "display_url": "pic.twitter.com/AzC4by1SZI",
                        "expanded_url": "https://twitter.com/trppyyy/status/861217317434171392/photo/1",
                        "type": "photo",
                        "sizes": {
                            "large": {
                                "w": 600,
                                "h": 337,
                                "resize": "fit"
                            },
                            "small": {
                                "w": 600,
                                "h": 337,
                                "resize": "fit"
                            },
                            "medium": {
                                "w": 600,
                                "h": 337,
                                "resize": "fit"
                            },
                            "thumb": {
                                "w": 150,
                                "h": 150,
                                "resize": "crop"
                            }
                        },
                        "features": {
                            "large": {
                                "faces": []
                            },
                            "small": {
                                "faces": []
                            },
                            "medium": {
                                "faces": []
                            },
                            "orig": {
                                "faces": []
                            }
                        }
                    }
                ]
            },
            "extended_entities": {
                "media": [
                    {
                        "id": 861217311549571074,
                        "id_str": "861217311549571074",
                        "indices": [
                            17,
                            40
                        ],
                        "media_url": "http://pbs.twimg.com/media/C_OolPlUQAIAIP6.jpg",
                        "media_url_https": "https://pbs.twimg.com/media/C_OolPlUQAIAIP6.jpg",
                        "url": "https://t.co/AzC4by1SZI",
                        "display_url": "pic.twitter.com/AzC4by1SZI",
                        "expanded_url": "https://twitter.com/trppyyy/status/861217317434171392/photo/1",
                        "type": "photo",
                        "sizes": {
                            "large": {
                                "w": 600,
                                "h": 337,
                                "resize": "fit"
                            },
                            "small": {
                                "w": 600,
                                "h": 337,
                                "resize": "fit"
                            },
                            "medium": {
                                "w": 600,
                                "h": 337,
                                "resize": "fit"
                            },
                            "thumb": {
                                "w": 150,
                                "h": 150,
                                "resize": "crop"
                            }
                        },
                        "features": {
                            "large": {
                                "faces": []
                            },
                            "small": {
                                "faces": []
                            },
                            "medium": {
                                "faces": []
                            },
                            "orig": {
                                "faces": []
                            }
                        }
                    }
                ]
            },
            "source": "<a href=\"http://twitter.com/download/iphone\" rel=\"nofollow\">Twitter for iPhone</a>",
            "in_reply_to_status_id": null,
            "in_reply_to_status_id_str": null,
            "in_reply_to_user_id": null,
            "in_reply_to_user_id_str": null,
            "in_reply_to_screen_name": null,
            "geo": null,
            "coordinates": null,
            "place": null,
            "contributors": null,
            "is_quote_status": false,
            "retweet_count": 77,
            "favorite_count": 138,
            "favorited": false,
            "retweeted": false,
            "possibly_sensitive": false,
            "lang": "ja",
            "supplemental_language": null
        },
        "is_quote_status": false,
        "retweet_count": 77,
        "favorite_count": 0,
        "favorited": false,
        "retweeted": false,
        "possibly_sensitive": false,
        "lang": "ja",
        "supplemental_language": null
    },
    "contributors_enabled": false,
    "is_translator": false,
    "is_translation_enabled": false,
    "profile_background_color": "F5F8FA",
    "profile_background_image_url": null,
    "profile_background_image_url_https": null,
    "profile_background_tile": false,
    "profile_image_url": "http://pbs.twimg.com/profile_images/833085924586070016/4csf5jr__normal.jpg",
    "profile_image_url_https": "https://pbs.twimg.com/profile_images/833085924586070016/4csf5jr__normal.jpg",
    "profile_banner_url": "https://pbs.twimg.com/profile_banners/833028716426993664/1487482318",
    "profile_link_color": "1DA1F2",
    "profile_sidebar_border_color": "C0DEED",
    "profile_sidebar_fill_color": "DDEEF6",
    "profile_text_color": "333333",
    "profile_use_background_image": true,
    "has_extended_profile": true,
    "default_profile": true,
    "default_profile_image": false,
    "has_custom_timelines": true,
    "can_media_tag": false,
    "followed_by": false,
    "following": false,
    "follow_request_sent": false,
    "notifications": false,
    "business_profile_state": "none",
    "customer_service_state": "none",
    "translator_type": "none"
}